CHANGELOG.rst
LICENSE.rst
MANIFEST.in
README.rst
setup.py
Relief.egg-info/PKG-INFO
Relief.egg-info/SOURCES.txt
Relief.egg-info/dependency_links.txt
Relief.egg-info/top_level.txt
docs/Makefile
docs/conf.py
docs/index.rst
docs/make.bat
docs/tutorial.rst
docs/_static/.gitignore
docs/_templates/.gitignore
docs/api/relief.rst
docs/api/validation.rst
docs/other/changelog.rst
docs/other/contributing.rst
docs/other/license.rst
relief/__init__.py
relief/_compat.py
relief/constants.py
relief/validation.py
relief/schema/__init__.py
relief/schema/core.py
relief/schema/mappings.py
relief/schema/meta.py
relief/schema/scalars.py
relief/schema/sequences.py
relief/utils/__init__.py
relief/utils/idd.py