Metadata-Version: 1.1
Name: Relief
Version: 2.1.0
Summary: datastructure validation
Home-page: https://github.com/DasIch/relief
Author: Daniel Neuhäuser
Author-email: ich@danielneuhaeuser.de
License: BSD
Platform: UNKNOWN
Classifier: License :: OSI Approved :: BSD License
Classifier: Operating System :: OS Independent
Classifier: Programming Language :: Python :: 2.6
Classifier: Programming Language :: Python :: 2.7
Classifier: Programming Language :: Python :: 3.3
Classifier: Programming Language :: Python :: Implementation :: PyPy
Classifier: Programming Language :: Python :: Implementation :: CPython
Classifier: Topic :: Software Development :: Libraries
